ltest.py
ltest_shift-0.1.1.dist-info/licenses/LICENSE
ltest_shift-0.1.1.dist-info/METADATA
ltest_shift-0.1.1.dist-info/WHEEL
ltest_shift-0.1.1.dist-info/top_level.txt
ltest_shift-0.1.1.dist-info/RECORD
