Metadata-Version: 2.4
Name: ltest-shift
Version: 0.1.1
Summary: Two-Sample L-Test: Shift-Invariant Cramér–von Mises Variant
Author-email: Jon Paul Lundquist <jplundquist@gmail.com>
License-Expression: MIT
Project-URL: Homepage, https://github.com/JonPaulLundquist/ltest
Project-URL: Issues, https://github.com/JonPaulLundquist/ltest/issues
Keywords: statistics,bootstrap,nonparametric,Cramer-von Mises,Anderson-Darling,two-sample
Classifier: Programming Language :: Python :: 3
Classifier: Operating System :: OS Independent
Classifier: Topic :: Scientific/Engineering :: Information Analysis
Requires-Python: >=3.8
License-File: LICENSE
Requires-Dist: numpy>=1.23
Requires-Dist: scipy>=1.9
Dynamic: license-file
